anclient/__init__.py
anclient/io/__init__.py
anclient/io/odysz/__init__.py
anclient/io/odysz/jclient.py
anclient_py3-0.2.5.dist-info/METADATA
anclient_py3-0.2.5.dist-info/WHEEL
anclient_py3-0.2.5.dist-info/entry_points.txt
anclient_py3-0.2.5.dist-info/top_level.txt
anclient_py3-0.2.5.dist-info/RECORD
