Metadata-Version: 2.4
Name: anclient.py3
Version: 0.2.5
Summary: Semantic-jserv Python Client
Author-email: Ody Z <odys.zhou@gmail.com>
License: Apache-2.0
Keywords: Semantics,AnClient,Semantier
Requires-Python: >=3.9
Requires-Dist: anson.py3>=0.3.6
Requires-Dist: semantics.py3
Requires-Dist: requests
Requires-Dist: typing_extensions
